{"name":"Vagrant Drupal 8","tagline":"Provides Vagrant machine with standard Drupal 8 configuration.","body":"## Overview\r\n\r\nThe VD8 project has been created to make sure developers have an easy method for boostrapping a local Drupal 8 development environment.\r\n\r\n## Roadmap\r\n\r\n* Phing targets.\r\n* Custom packer image to shorten provision time.\r\n\r\n## Requirements\r\n\r\n### Virtualbox (4.3.6)\r\n\r\nVirtualbox can be downloaded and installed from:\r\n\r\nhttps://www.virtualbox.org/wiki/Downloads\r\n\r\n### Vagrant (1.3 to 1.5)\r\n\r\nVagrant can be downloaded and installed from:\r\n\r\nhttp://www.vagrantup.com/downloads.html\r\n\r\nThis also required the autonetwork and hostsupdater plugins which can be installed by:\r\n\r\n```\r\n$ vagrant plugin install vagrant-hostsupdater\r\n$ vagrant plugin install vagrant-auto_network\r\n```\r\n\r\n#### Plugins\r\n\r\nThese are software versions we know work:\r\n\r\n* Vagrant Hostupdater: 0.0.11\r\n* Vagrant Auto-network: 0.2.1\r\n\r\n#### Usage\r\n\r\nThe machine can can be booted by the following command:\r\n\r\n```\r\n$ vagrant up\r\n```\r\n\r\nThe host will be provisioned automatically on the first `vagrant up`. If you\r\nwish to rerun the provision that can be done with the following command:\r\n\r\n```\r\n$ vagrant provision\r\n```\r\n\r\nMore vagrant commands and documenation can be found here:\r\n\r\nhttp://docs.vagrantup.com/v2\r\n\r\n## Local DNS\r\n\r\nWE REQUIRE THE \"Vagrant Auto-network\" PLUGIN AS MENTIONED ABOVE.\r\n\r\n## Drupal\r\n\r\nCheckout the latest HEAD of Drupal 8:\r\n\r\n```\r\n$ git clone --branch 8.0.x http://git.drupal.org/project/drupal.git app\r\n```\r\n\r\nTo install\r\n\r\n```\r\n$ phing reinstall\r\n```\r\n\r\nThe above command can be run as many times as you like. It provides a good\r\nworkflow for developing and testing.\r\n","google":"","note":"Don't delete this file! It's used internally to help with page regeneration."}